MySQL_CLI_NLP/__init__.py
MySQL_CLI_NLP/cli.py
MySQL_CLI_NLP/database.py
MySQL_CLI_NLP/exceptions.py
MySQL_CLI_NLP/nlp_processor.py
MySQL_CLI_NLP/query_builder.py
MySQL_CLI_NLP/schema.py
MySQL_NLP_CLI-1.0.0.dist-info/LICENSE
MySQL_NLP_CLI-1.0.0.dist-info/METADATA
MySQL_NLP_CLI-1.0.0.dist-info/WHEEL
MySQL_NLP_CLI-1.0.0.dist-info/top_level.txt
MySQL_NLP_CLI-1.0.0.dist-info/RECORD
