Metadata-Version: 2.2
Name: MySQL_NLP_CLI
Version: 1.0.0
Summary: A Python package that allows to use the CLI and Natural Language processing to write MySQL queries.
Author: Kunaal Gadhalay
Author-email: <kunaalgadhalay93@gmail.com>
Keywords: python,cli,NLP,mysql,Command,Line,Interface,Natural,Language,Processing
Classifier: Development Status :: 1 - Planning
Classifier: Intended Audience :: Developers
Classifier: Programming Language :: Python :: 3
Classifier: Operating System :: Unix
Classifier: Operating System :: MacOS :: MacOS X
Classifier: Operating System :: Microsoft :: Windows
Requires-Python: >=3.6
License-File: LICENSE
Requires-Dist: venv
Requires-Dist: argparse
Requires-Dist: logging
Requires-Dist: pathlib
Requires-Dist: re
Requires-Dist: getpass
Requires-Dist: mysql-connector-python
Requires-Dist: spacy
Requires-Dist: download
Requires-Dist: en_core_web_smtyping
Requires-Dist: dataclasses
Dynamic: author
Dynamic: author-email
Dynamic: classifier
Dynamic: description
Dynamic: description-content-type
Dynamic: keywords
Dynamic: requires-dist
Dynamic: requires-python
Dynamic: summary
